log_decorator/__init__.py
log_decorator/async_log.py
log_decorator/log.py
log_decorator/log_formatter.py
verbose_log_decorator-1.1.2.dist-info/LICENSE
verbose_log_decorator-1.1.2.dist-info/METADATA
verbose_log_decorator-1.1.2.dist-info/WHEEL
verbose_log_decorator-1.1.2.dist-info/top_level.txt
verbose_log_decorator-1.1.2.dist-info/RECORD
