Metadata-Version: 2.1
Name: verbose-log-decorator
Version: 1.1.2
Summary: decorators to log function calls in verbose manner
Home-page: https://github.com/Pavel-Egorov/log_decorator
Author: Pavel Egorov
Author-email: paveg.sp@gmail.com
Maintainer: Pavel Egorov
Maintainer-email: paveg.sp@gmail.com
License: Apache
Keywords: logging
Classifier: Development Status :: 5 - Production/Stable
Classifier: Intended Audience :: Developers
Classifier: Natural Language :: English
Classifier: License :: OSI Approved :: Apache Software License
Classifier: Operating System :: OS Independent
Classifier: Programming Language :: Python
Classifier: Programming Language :: Python :: 3.6
Classifier: Programming Language :: Python :: 3.7
Classifier: Programming Language :: Python :: 3.8
Classifier: Programming Language :: Python :: 3.9
Classifier: Programming Language :: Python :: 3.10
Classifier: Topic :: Software Development :: Libraries :: Python Modules
License-File: LICENSE
Requires-Dist: wrapt
Requires-Dist: ujson
